demarches_simpy/__init__.py
demarches_simpy/actions.py
demarches_simpy/connection.py
demarches_simpy/demarche.py
demarches_simpy/dossier.py
demarches_simpy/fields.py
demarches_simpy/interfaces.py
demarches_simpy/utils.py
demarches_simpy/query/actions.graphql
demarches_simpy/query/demarche.graphql
demarches_simpy/query/dossier_data.graphql
demarches_simpy/query/empty.graphql
demarches_simpy/query/fields.graphql
demarches_simpy/query/send_message.graphql
demarches_simpy-0.0.18.dist-info/LICENSE
demarches_simpy-0.0.18.dist-info/METADATA
demarches_simpy-0.0.18.dist-info/WHEEL
demarches_simpy-0.0.18.dist-info/top_level.txt
demarches_simpy-0.0.18.dist-info/RECORD
