Metadata-Version: 2.1
Name: demarches-simpy
Version: 0.0.18
Summary: A simple python wrapper for the demarches-simplifiees.fr API
Author-email: "Esteban Rodriguez (Z3ZEL)" <contact@rodriguez-esteban.com>
Project-URL: Homepage, https://github.com/Z3ZEL/demarches-simplifiees
Project-URL: Bug Tracker, https://github.com/pypa/sampleproject/issues
Classifier: Programming Language :: Python :: 3
Classifier: License :: OSI Approved :: MIT License
Classifier: Operating System :: OS Independent
Requires-Python: >=3.9
License-File: LICENSE
Requires-Dist: requests
Requires-Dist: shapely >=2.0.1
Requires-Dist: pytz
